pytest_regression/__init__.py
pytest_regression/plugin.py
pytest_batch_regression-0.1.5.dist-info/LICENSE
pytest_batch_regression-0.1.5.dist-info/METADATA
pytest_batch_regression-0.1.5.dist-info/WHEEL
pytest_batch_regression-0.1.5.dist-info/entry_points.txt
pytest_batch_regression-0.1.5.dist-info/top_level.txt
pytest_batch_regression-0.1.5.dist-info/RECORD
